blueprint_cli/__init__.py
blueprint_cli/commands/__init__.py
blueprint_cli/commands/check.py
blueprint_cli/commands/init.py
blueprint_cli/core/__init__.py
blueprint_cli/core/agent_config.py
blueprint_cli/core/cli.py
blueprint_cli/core/step_tracker.py
blueprint_cli/core/utils.py
blueprint_cli/services/__init__.py
blueprint_cli/services/git.py
blueprint_cli/services/github.py
blueprint_kit-1.0.75.dist-info/METADATA
blueprint_kit-1.0.75.dist-info/WHEEL
blueprint_kit-1.0.75.dist-info/entry_points.txt
blueprint_kit-1.0.75.dist-info/RECORD
