Metadata-Version: 2.4
Name: blueprint-kit
Version: 1.0.75
Summary: Blueprint CLI, part of Blueprint Kit. A tool to bootstrap your projects for Blueprint-Driven Development (BDD).
Project-URL: Homepage, https://github.com/nom-nom-hub/blueprint-kit
Project-URL: Repository, https://github.com/nom-nom-hub/blueprint-kit
Project-URL: Documentation, https://github.com/nom-nom-hub/blueprint-kit
Author-email: Teck <teckmillion17@gmail.com>
Requires-Python: >=3.10
Requires-Dist: httpx[socks]
Requires-Dist: platformdirs
Requires-Dist: readchar
Requires-Dist: rich
Requires-Dist: truststore>=0.10.4
Requires-Dist: typer
